prompt_template_to_messages/__init__.py
prompt_template_to_messages/constants.py
prompt_template_to_messages/exceptions.py
prompt_template_to_messages/models.py
prompt_template_to_messages/parsing.py
prompt_template_to_messages/scope.py
prompt_template_to_messages/translators.py
prompt_template_to_messages-0.1.0.dist-info/METADATA
prompt_template_to_messages-0.1.0.dist-info/WHEEL
prompt_template_to_messages-0.1.0.dist-info/entry_points.txt
prompt_template_to_messages-0.1.0.dist-info/licenses/LICENSE
prompt_template_to_messages-0.1.0.dist-info/RECORD
