Metadata-Version: 2.4
Name: prompt-template-to-messages
Version: 0.1.0
Summary: Post-process rendered Jinja2 templates and compile them into OpenAI messages
Project-URL: Homepage, https://github.com/eggachecat/prompt-template-to-messages
Project-URL: Repository, https://github.com/eggachecat/prompt-template-to-messages.git
Project-URL: Issues, https://github.com/eggachecat/prompt-template-to-messages/issues
Author-email: eggachecat <ao.sun@outlook.com>
License: MIT License
License-File: LICENSE
Keywords: jinja2,llm,messages,openai,prompt,template
Classifier: Development Status :: 3 - Alpha
Classifier: Intended Audience :: Developers
Classifier: License :: OSI Approved :: MIT License
Classifier: Programming Language :: Python
Classifier: Programming Language :: Python :: 3
Classifier: Programming Language :: Python :: 3 :: Only
Classifier: Programming Language :: Python :: 3.9
Classifier: Programming Language :: Python :: 3.10
Classifier: Programming Language :: Python :: 3.11
Classifier: Programming Language :: Python :: 3.12
Classifier: Topic :: Software Development :: Libraries :: Python Modules
Requires-Python: >=3.9
Requires-Dist: beautifulsoup4>=4.12
Requires-Dist: click>=8.1
Requires-Dist: jinja2>=3.1
Provides-Extra: dev
Requires-Dist: build>=0.10; extra == 'dev'
Requires-Dist: bump2version>=1.0; extra == 'dev'
Requires-Dist: mypy>=1.0; extra == 'dev'
Requires-Dist: pytest-cov>=4.1; extra == 'dev'
Requires-Dist: pytest>=7.4; extra == 'dev'
Requires-Dist: ruff>=0.1; extra == 'dev'
Requires-Dist: twine>=4.0; extra == 'dev'
Provides-Extra: test
Requires-Dist: pytest-cov>=4.1; extra == 'test'
Requires-Dist: pytest>=7.4; extra == 'test'
